[{"onumber":"0918111222","oobj":{"orderNumber":"0918111222","orderName":"aa","orderEmail":"bb","userphone":"0918111222","imageFile":"C:\\Users\\Eugene\\Documents\\myExpressApp\\dl/uploads/0918111222.jpg","orderDetail":[{"playerName":"cc","playerNumber":"4","shirtSize":"S","paintSize":"S"}]}},{"onumber":"0918999000","oobj":{"orderNumber":"0918999000","orderName":"eugeneCheng","orderEmail":"eu@gmail.com","userphone":"0918999000","imageFile":"C:\\Users\\Eugene\\Documents\\myExpressApp\\dl/uploads/0918999000.jpg","orderDetail":[{"playerName":"小明","playerNumber":"12","shirtSize":"M","paintSize":"S"},{"playerName":"阿財","playerNumber":"13","shirtSize":"L","paintSize":"M"}]}}]